graphscope/VERSION
graphscope/__init__.py
graphscope/version.py
graphscope/config.py
graphscope/nx/conftest.py
graphscope/nx/convert.py
graphscope/nx/__init__.py
graphscope/nx/relabel.py
graphscope/nx/convert_matrix.py
graphscope/nx/algorithms/__init__.py
graphscope/nx/algorithms/builtin.py
graphscope/nx/algorithms/tests/__init__.py
graphscope/nx/algorithms/tests/builtin/test_core.py
graphscope/nx/algorithms/tests/builtin/test_betweenness_centrality.py
graphscope/nx/algorithms/tests/builtin/test_shortest_paths.py
graphscope/nx/algorithms/tests/builtin/test_degree_centrality.py
graphscope/nx/algorithms/tests/builtin/test_eigenvector_centrality.py
graphscope/nx/algorithms/tests/builtin/__init__.py
graphscope/nx/algorithms/tests/builtin/test_degree_connectivity.py
graphscope/nx/algorithms/tests/builtin/test_cluster.py
graphscope/nx/algorithms/tests/builtin/test_hits.py
graphscope/nx/algorithms/tests/builtin/test_voterank.py
graphscope/nx/algorithms/tests/builtin/test_dfs.py
graphscope/nx/algorithms/tests/builtin/test_boundary.py
graphscope/nx/algorithms/tests/builtin/test_bfs.py
graphscope/nx/algorithms/tests/builtin/test_pagerank.py
graphscope/nx/algorithms/tests/builtin/test_degree_assortativity.py
graphscope/nx/algorithms/tests/builtin/test_simple_paths.py
graphscope/nx/algorithms/tests/builtin/test_closeness_centrality.py
graphscope/nx/algorithms/tests/builtin/test_attribute_assortativity.py
graphscope/nx/algorithms/tests/builtin/test_katz_centrality.py
graphscope/nx/algorithms/tests/forward/test_structuralholes.py
graphscope/nx/algorithms/tests/forward/test_lowest_common_ancestors.py
graphscope/nx/algorithms/tests/forward/test_wiener.py
graphscope/nx/algorithms/tests/forward/test_smetric.py
graphscope/nx/algorithms/tests/forward/test_non_randomness.py
graphscope/nx/algorithms/tests/forward/test_core.py
graphscope/nx/algorithms/tests/forward/test_tournament.py
graphscope/nx/algorithms/tests/forward/test_assortativity.py
graphscope_client-0.29.0.dist-info/METADATA
graphscope_client-0.29.0.dist-info/RECORD
graphscope_client-0.29.0.dist-info/top_level.txt
graphscope_client-0.29.0.dist-info/WHEEL
