Metadata-Version: 2.1
Name: graphscope-client
Version: 0.29.0
Summary: GraphScope: A One-Stop Large-Scale Graph Computing System from Alibaba
Home-page: https://github.com/alibaba/GraphScope
Author: Alibaba Damo Academy
Author-email: graphscope@alibaba-inc.com
License: Apache License 2.0
Project-URL: Documentation, https://graphscope.io/docs
Project-URL: Source, https://github.com/alibaba/GraphScope
Project-URL: Tracker, https://github.com/alibaba/GraphScope/issues
Keywords: Graph,Large-Scale,Distributed Computing
Classifier: Development Status :: 5 - Production/Stable
Classifier: Intended Audience :: Developers
Classifier: Intended Audience :: Science/Research
Classifier: License :: OSI Approved :: Apache Software License
Classifier: Topic :: Software Development :: Libraries
Classifier: Topic :: System :: Distributed Computing
Classifier: Operating System :: MacOS :: MacOS X
Classifier: Operating System :: POSIX
Classifier: Programming Language :: Python
Classifier: Programming Language :: Python :: 3
Classifier: Programming Language :: Python :: 3.7
Classifier: Programming Language :: Python :: 3.8
Classifier: Programming Language :: Python :: 3.9
Classifier: Programming Language :: Python :: 3.10
Classifier: Programming Language :: Python :: 3.11
Requires-Dist: Cython>=3.0.0b3
Requires-Dist: gremlinpython==3.7.0
Requires-Dist: grpcio>=1.49
Requires-Dist: grpcio-tools>=1.49
Requires-Dist: kubernetes>=24.2.0
Requires-Dist: msgpack>=1.0.5
Requires-Dist: mypy-protobuf>=3.4.0
Requires-Dist: neo4j==5.10.0
Requires-Dist: nest-asyncio
Requires-Dist: numpy<2.0.0
Requires-Dist: orjson
Requires-Dist: packaging
Requires-Dist: pandas<=2.0.3
Requires-Dist: protobuf>=4
Requires-Dist: psutil
Requires-Dist: pyarrow>=10
Requires-Dist: PyYAML
Requires-Dist: rich
Requires-Dist: tqdm
Requires-Dist: simple-parsing
Requires-Dist: graphscope-flex>=0.27.0
Requires-Dist: pysimdjson<6; python_version < "3.11"
Requires-Dist: networkx==2.6.0; python_version < "3.8"
Requires-Dist: pysimdjson>=6; python_version >= "3.11"
Requires-Dist: ujson; python_version >= "3.11"
Requires-Dist: networkx==2.8.0; python_version >= "3.8"
Requires-Dist: vineyard>=0.16.3; sys_platform != "win32"
Provides-Extra: dev
Requires-Dist: black>=23.3.0; extra == "dev"
Requires-Dist: breathe>4.30; extra == "dev"
Requires-Dist: docutils==0.20.1; extra == "dev"
Requires-Dist: flake8==4.0.1; extra == "dev"
Requires-Dist: furo; extra == "dev"
Requires-Dist: isort==5.10.1; extra == "dev"
Requires-Dist: jinja2>=3.1.0; extra == "dev"
Requires-Dist: linkify-it-py; extra == "dev"
Requires-Dist: myst-parser>=0.13.0; extra == "dev"
Requires-Dist: pylint; extra == "dev"
Requires-Dist: pytest; extra == "dev"
Requires-Dist: pytest-cov; extra == "dev"
Requires-Dist: pytest-xdist; extra == "dev"
Requires-Dist: pytest-timeout; extra == "dev"
Requires-Dist: Pygments>=2.4.1; extra == "dev"
Requires-Dist: sphinx>=7.1.2; extra == "dev"
Requires-Dist: sphinx-copybutton; extra == "dev"
Requires-Dist: sphinx-panels; extra == "dev"
Requires-Dist: sphinxemoji; extra == "dev"
Requires-Dist: sphinxext-opengraph; extra == "dev"
Requires-Dist: tomli; extra == "dev"
Requires-Dist: wheel; extra == "dev"
Requires-Dist: setuptools==70.0.0; extra == "dev"
Requires-Dist: pyopenapigenerator==7.8.0; extra == "dev"
